[
    {
        "name": "Take a small break!",
        "description": "Take a small break please!",
        "interval": "PT20S",
        "duration": "PT8S",
        "startSoundPath": "break-start.wav",
        "endSoundPath": "break-end.wav",
        "reminders": [
            {
                "timeBefore": "PT3S",
                "soundPath": "1min-reminder.wav"
            },
            {
                "timeBefore": "PT10S",
                "soundPath": "5min-reminder.wav"
            }
        ]
    },
    {
        "name": "Take a BIG BREAK!",
        "description": "Take a BIG break please!",
        "interval": "PT40S",
        "duration": "PT8S",
        "startSoundPath": "break-start.wav",
        "endSoundPath": "break-end.wav",
        "reminders": [
            {
                "timeBefore": "PT3S",
                "soundPath": "1min-reminder.wav"
            },
            {
                "timeBefore": "PT10S",
                "soundPath": "5min-reminder.wav"
            }
        ]
    }
]